{
  "configuration_description": "Goose-wing sailing configuration",
  "configuration_name": "goosewing",
  
  "required": [
    "render"
  ],
  
  "sail_camber_biru": 10000,
  "sail_camber_kuning": 10000,
  "sail_angle_biru": 45,
  "sail_angle_kuning": -45,
  "rig_rotation_biru": 90,
  "rig_rotation_kuning": 90,
  "rudder_rotation_biru": 0,
  "rudder_raised_biru": true,
  "rudder_rotation_kuning": 0,
  "rudder_raised_kuning": false,
  "reefing_percentage_biru": 0,
  "reefing_percentage_kuning": 0
}
